kimportsetup/__init__.py
kimportsetup/main.py
kimportsetup-0.1.1.dist-info/METADATA
kimportsetup-0.1.1.dist-info/WHEEL
kimportsetup-0.1.1.dist-info/entry_points.txt
kimportsetup-0.1.1.dist-info/top_level.txt
kimportsetup-0.1.1.dist-info/RECORD
